serialbox/__init__.py
serialbox/admin.py
serialbox/admin_actions.py
serialbox/apps.py
serialbox/discovery.py
serialbox/errors.py
serialbox/flavor_packs.py
serialbox/models.py
serialbox/serialbox_settings.py
serialbox/utils.py
serialbox/viewsets.py
serialbox/api/__init__.py
serialbox/api/errors.py
serialbox/api/routers.py
serialbox/api/serializers.py
serialbox/api/urls.py
serialbox/api/views.py
serialbox/api/viewsets.py
serialbox/generators/__init__.py
serialbox/generators/common.py
serialbox/generators/errors.py
serialbox/generators/sequential.py
serialbox/management/__init__.py
serialbox/management/commands/__init__.py
serialbox/management/commands/create_response_rule.py
serialbox/management/commands/load_serialbox_auth.py
serialbox/management/commands/load_test_pools.py
serialbox/management/commands/utils.py
serialbox/migrations/0001_initial.py
serialbox/migrations/0002_randomizedregion.py
serialbox/migrations/0003_auto_20180725_1958.py
serialbox/migrations/0004_auto_20181015_2115.py
serialbox/migrations/0005_auto_20181031_1738.py
serialbox/migrations/0006_auto_20190128_1552.py
serialbox/migrations/0007_auto_20191219_1709.py
serialbox/migrations/0008_randomizedregion.py
serialbox/migrations/0009_auto_20210818_1601.py
serialbox/migrations/0010_auto_20210818_1903.py
serialbox/migrations/0011_auto_20210818_2117.py
serialbox/migrations/0012_alter_pool_id_alter_randomizedregion_id_and_more.py
serialbox/migrations/__init__.py
serialbox/renderers/__init__.py
serialbox/response/__init__.py
serialbox/rules/__init__.py
serialbox/rules/common.py
serialbox/rules/errors.py
serialbox/rules/limits.py
serialbox/rules/steps.py
serialbox/static/bower_components/bootswatch-dist/.bower.json
serialbox/static/bower_components/bootswatch-dist/bower.json
serialbox/static/bower_components/bootswatch-dist/css/bootstrap.css
serialbox/static/bower_components/bootswatch-dist/css/bootstrap.min.css
serialbox/static/bower_components/bootswatch-dist/fonts/glyphicons-halflings-regular.eot
serialbox-3.0.9.dist-info/AUTHORS
serialbox-3.0.9.dist-info/LICENSE.md
serialbox-3.0.9.dist-info/METADATA
serialbox-3.0.9.dist-info/WHEEL
serialbox-3.0.9.dist-info/top_level.txt
serialbox-3.0.9.dist-info/RECORD
