Metadata-Version: 2.1
Name: serialbox
Version: 3.0.9
Summary: Serial Number Distribution Made Easy.
Home-page: http://www.serial-lab.com
Author: SerialLab Corp
Author-email: slab@serial-lab.com
License: GPL
Platform: UNKNOWN
Classifier: License :: OSI Approved :: GNU Affero General Public License v3 or later (AGPLv3+)
Classifier: Development Status :: 5 - Production/Stable
Classifier: Framework :: Django
Classifier: Framework :: Django :: 2.0
Classifier: Intended Audience :: Healthcare Industry
Classifier: Intended Audience :: Manufacturing
Classifier: Intended Audience :: Developers
Classifier: Natural Language :: English
Classifier: Programming Language :: Python :: 3
Classifier: Programming Language :: Python :: 3.5
Classifier: Programming Language :: Python :: 3.6
Classifier: Natural Language :: English
Requires-Dist: django
Requires-Dist: djangorestframework
Requires-Dist: djangorestframework-csv
Requires-Dist: djangorestframework-xml
Requires-Dist: Markdown
Requires-Dist: decorator
Requires-Dist: six
Requires-Dist: docutils
